setup.py
media/Media.py
media/__init__.py
media/sorter.py
media/yesno.py
sorter.egg-info/PKG-INFO
sorter.egg-info/SOURCES.txt
sorter.egg-info/dependency_links.txt
sorter.egg-info/entry_points.txt
sorter.egg-info/requires.txt
sorter.egg-info/top_level.txt