Metadata-Version: 1.1
Name: sorter
Version: 0.5
Summary: A program to rename media files and store them
Home-page: https://bitbucket.org/andxet/sorter
Author: Andrea Peretti
Author-email: peretti.and@gmail.com
License: MIT
Keywords: tv_series movies files
Platform: UNKNOWN
Classifier: Development Status :: 3 - Alpha
Classifier: Intended Audience :: End Users/Desktop
Classifier: License :: OSI Approved :: MIT License
Classifier: Programming Language :: Python :: 2
Classifier: Programming Language :: Python :: 2.6
Classifier: Programming Language :: Python :: 2.7
